libpfapi/__init__.py
libpfapi/api.py
libpfapi/exceptions.py
libpfapi/task.py
libpfapi/utils.py
libpfapi/models/__init__.py
libpfapi/models/base.py
libpfapi/models/baselayer.py
libpfapi/models/capabilities.py
libpfapi/models/category.py
libpfapi/models/corridor.py
libpfapi/models/cost.py
libpfapi/models/layer.py
libpfapi/models/layerconfig.py
libpfapi/models/project.py
libpfapi/models/rmap.py
libpfapi/models/routing.py
libpfapi/models/scenario.py
libpfapi/models/scenarioconfig.py
libpfapi/models/scenariopath.py
libpfapi-0.4.2.dist-info/licenses/LICENSE
libpfapi-0.4.2.dist-info/METADATA
libpfapi-0.4.2.dist-info/WHEEL
libpfapi-0.4.2.dist-info/top_level.txt
libpfapi-0.4.2.dist-info/RECORD
