Metadata-Version: 2.4
Name: libpfapi
Version: 0.4.2
Summary: Base library providing basic pathfinder REST api access utilities
Author-email: Jordi Castells <jordi.castells@gilytics.com>, Rafael Ruiz <rafael.romero@gilytics.com>
Project-URL: Homepage, https://www.gilytics.com/
Project-URL: Issues, https://www.gilytics.com/faqs
Classifier: Programming Language :: Python :: 3
Classifier: License :: OSI Approved :: MIT License
Classifier: Operating System :: OS Independent
Requires-Python: >=3.8
License-File: LICENSE
Dynamic: license-file
